dylanswordsegmenter/__init__.py
dylanswordsegmenter/csv_example.py
dylanswordsegmenter/example.py
dylanswordsegmenter/segmenter.py
dylanswordsegmenter/test.py
dylanswordsegmenter-0.1.4.dist-info/METADATA
dylanswordsegmenter-0.1.4.dist-info/WHEEL
dylanswordsegmenter-0.1.4.dist-info/top_level.txt
dylanswordsegmenter-0.1.4.dist-info/RECORD
